{
  "db_name": "SQLite",
  "query": "SELECT * FROM git_command_log",
  "describe": {
    "columns": [
      {
        "name": "id",
        "ordinal": 0,
        "type_info": "Int64"
      },
      {
        "name": "command",
        "ordinal": 1,
        "type_info": "Text"
      },
      {
        "name": "created_at",
        "ordinal": 2,
        "type_info": "Datetime"
      },
      {
        "name": "repository_id",
        "ordinal": 3,
        "type_info": "Int64"
      }
    ],
    "parameters": {
      "Right": 0
    },
    "nullable": [
      false,
      false,
      false,
      false
    ]
  },
  "hash": "02075224dd4f38b3b14c36e2f6822505495a09b82e07deb9da498a051915dcb4"
}
